fpage/LICENSE
fpage/MANIFEST.in
fpage/fpage.py
fpage/setup.cfg
fpage/src/app.py
fpage/src/config.py
fpage/src/lib/__init__.py
fpage/src/lib/jsdict.py
fpage/src/lib/patch.py
fpage/src/lib/pvpatch.py
fpage/src/lib/state_obj.py
fpage/src/model/__init__.py
fpage/src/model/models.py
fpage/src/model/test.py
fpage/src/model/user.py
fpage/src/model_peewee/__init__.py
fpage/src/model_peewee/models.py
fpage/src/model_peewee/test.py
fpage/src/model_peewee/user.py
fpage/src/static/css/style.css
fpage/src/static/js/main.js
fpage/src/templates/about.html
fpage/src/templates/base.html
fpage/src/templates/index.html
fpage/src/templates/user/signin.html
fpage/src/templates/user/signup.html
fpage/src/templates_jinja2/about.html
fpage/src/templates_jinja2/base.html
fpage/src/templates_jinja2/index.html
fpage/src/templates_jinja2/user/signin.html
fpage/src/templates_jinja2/user/signup.html
fpage/src/templates_tornado/about.html
fpage/src/templates_tornado/base.html
fpage/src/templates_tornado/index.html
fpage/src/templates_tornado/user/signin.html
fpage/src/templates_tornado/user/signup.html
fpage/src/view/__init__.py
fpage/src/view/index.py
fpage/src/view/user.py
fpage/src/view/views.py
fpage-1.2.1.dist-info/DESCRIPTION.rst
fpage-1.2.1.dist-info/METADATA
fpage-1.2.1.dist-info/RECORD
fpage-1.2.1.dist-info/WHEEL
fpage-1.2.1.dist-info/entry_points.txt
fpage-1.2.1.dist-info/metadata.json
fpage-1.2.1.dist-info/top_level.txt
